pyinsurance/__init__.py
pyinsurance/data/__init__.py
pyinsurance/data/utils.py
pyinsurance/data/IRX/__init__.py
pyinsurance/data/IRX/irx.csv.gz
pyinsurance/data/sp500/__init__.py
pyinsurance/data/sp500/sp500.csv.gz
pyinsurance/metrics/__init__.py
pyinsurance/metrics/metrics.py
pyinsurance/portfolio/__init__.py
pyinsurance/portfolio/_tipp.c
pyinsurance/portfolio/_tipp.cpython-313-x86_64-linux-gnu.so
pyinsurance/portfolio/_tipp.pyi
pyinsurance/portfolio/_tipp.pyx
pyinsurance/portfolio/base.py
pyinsurance/portfolio/tipp.py
pyinsurance/stats/__init__.py
pyinsurance/stats/capm.py
pyinsurance-2.0.0.dist-info/METADATA
pyinsurance-2.0.0.dist-info/WHEEL
pyinsurance-2.0.0.dist-info/top_level.txt
pyinsurance-2.0.0.dist-info/RECORD
pyinsurance-2.0.0.dist-info/licenses/LICENSE.txt
