Metadata-Version: 2.4
Name: pyinsurance
Version: 2.0.0
Summary: Insurance portfolio management tools
Requires-Python: >=3.10
License-File: LICENSE.txt
Requires-Dist: cython>=3.0.12
Requires-Dist: numpy>=2.2.5
Requires-Dist: scipy>=1.15.2
Requires-Dist: statsmodels>=0.14.4
Requires-Dist: pandas>=2.2.2
Requires-Dist: pandas-stubs>=2.2.2
Requires-Dist: scipy-stubs>=1.15.2
Provides-Extra: dev
Requires-Dist: pytest>=7.0.0; extra == "dev"
Requires-Dist: pytest-cov>=4.0.0; extra == "dev"
Requires-Dist: mypy>=1.0.0; extra == "dev"
Requires-Dist: black>=23.0.0; extra == "dev"
Requires-Dist: isort>=5.0.0; extra == "dev"
Requires-Dist: flake8>=5.0.0; extra == "dev"
Dynamic: license-file
